<?xml version="1.0"?>
<projectProfile type="default" version="1.12.4">
  <projectDirectory>
    <projectProfileFile filesystemName=".zfproject.xml"/>
    <applicationDirectory classNamePrefix="Application_">
      <configsDirectory>
        <applicationConfigFile type="ini"/>
      </configsDirectory>
      <controllersDirectory>
        <controllerFile controllerName="Index">
          <actionMethod actionName="index"/>
        </controllerFile>
        <controllerFile controllerName="Error"/>
        <controllerFile controllerName="Category">
          <actionMethod actionName="index"/>
          <actionMethod actionName="add"/>
          <actionMethod actionName="edit"/>
        </controllerFile>
        <controllerFile controllerName="Product">
          <actionMethod actionName="index"/>
          <actionMethod actionName="add"/>
          <actionMethod actionName="edit"/>
        </controllerFile>
        <controllerFile controllerName="Cart">
          <actionMethod actionName="index"/>
          <actionMethod actionName="add"/>
          <actionMethod actionName="remove"/>
          <actionMethod actionName="empty"/>
          <actionMethod actionName="show"/>
          <actionMethod actionName="set"/>
        </controllerFile>
      </controllersDirectory>
      <formsDirectory>
        <formFile formName="Category"/>
        <formFile formName="Product"/>
      </formsDirectory>
      <layoutsDirectory>
        <layoutScriptsDirectory>
          <layoutScriptFile layoutName="layout"/>
        </layoutScriptsDirectory>
      </layoutsDirectory>
      <modelsDirectory>
        <dbTableDirectory>
          <dbTableFile dbTableName="Product"/>
          <dbTableFile dbTableName="Category"/>
          <dbTableFile dbTableName="ProductToCategory"/>
        </dbTableDirectory>
        <modelFile modelName="Product"/>
        <modelFile modelName="Category"/>
      </modelsDirectory>
      <modulesDirectory enabled="false"/>
      <servicesDirectory enabled="false"/>
      <viewsDirectory>
        <viewScriptsDirectory>
          <viewControllerScriptsDirectory forControllerName="Index">
            <viewScriptFile forActionName="index"/>
          </viewControllerScriptsDirectory>
          <viewControllerScriptsDirectory forControllerName="Error">
            <viewScriptFile forActionName="error"/>
          </viewControllerScriptsDirectory>
          <viewControllerScriptsDirectory forControllerName="Category">
            <viewScriptFile forActionName="index"/>
          </viewControllerScriptsDirectory>
          <viewControllerScriptsDirectory forControllerName="Category">
            <viewScriptFile forActionName="add"/>
          </viewControllerScriptsDirectory>
          <viewControllerScriptsDirectory forControllerName="Category">
            <viewScriptFile forActionName="edit"/>
          </viewControllerScriptsDirectory>
          <viewControllerScriptsDirectory forControllerName="Product">
            <viewScriptFile forActionName="index"/>
          </viewControllerScriptsDirectory>
          <viewControllerScriptsDirectory forControllerName="Product">
            <viewScriptFile forActionName="add"/>
          </viewControllerScriptsDirectory>
          <viewControllerScriptsDirectory forControllerName="Product">
            <viewScriptFile forActionName="edit"/>
          </viewControllerScriptsDirectory>
          <viewControllerScriptsDirectory forControllerName="Cart">
            <viewScriptFile forActionName="index"/>
          </viewControllerScriptsDirectory>
          <viewControllerScriptsDirectory forControllerName="Cart">
            <viewScriptFile forActionName="add"/>
          </viewControllerScriptsDirectory>
          <viewControllerScriptsDirectory forControllerName="Cart">
            <viewScriptFile forActionName="remove"/>
          </viewControllerScriptsDirectory>
          <viewControllerScriptsDirectory forControllerName="Cart">
            <viewScriptFile forActionName="empty"/>
          </viewControllerScriptsDirectory>
          <viewControllerScriptsDirectory forControllerName="Cart">
            <viewScriptFile forActionName="show"/>
          </viewControllerScriptsDirectory>
          <viewControllerScriptsDirectory forControllerName="Cart">
            <viewScriptFile forActionName="set"/>
          </viewControllerScriptsDirectory>
        </viewScriptsDirectory>
        <viewHelpersDirectory/>
        <viewFiltersDirectory enabled="false"/>
      </viewsDirectory>
      <bootstrapFile filesystemName="Bootstrap.php"/>
    </applicationDirectory>
    <dataDirectory enabled="false">
      <cacheDirectory enabled="false"/>
      <searchIndexesDirectory enabled="false"/>
      <localesDirectory enabled="false"/>
      <logsDirectory enabled="false"/>
      <sessionsDirectory enabled="false"/>
      <uploadsDirectory enabled="false"/>
    </dataDirectory>
    <docsDirectory>
      <file filesystemName="README.txt"/>
    </docsDirectory>
    <libraryDirectory>
      <zfStandardLibraryDirectory enabled="false"/>
    </libraryDirectory>
    <publicDirectory>
      <publicStylesheetsDirectory enabled="false"/>
      <publicScriptsDirectory enabled="false"/>
      <publicImagesDirectory enabled="false"/>
      <publicIndexFile filesystemName="index.php"/>
      <htaccessFile filesystemName=".htaccess"/>
    </publicDirectory>
    <projectProvidersDirectory enabled="false"/>
    <temporaryDirectory enabled="false"/>
    <testsDirectory>
      <testPHPUnitConfigFile filesystemName="phpunit.xml"/>
      <testPHPUnitBootstrapFile filesystemName="bootstrap.php"/>
      <testApplicationDirectory>
        <testApplicationControllerDirectory>
          <testApplicationControllerFile forControllerName="Index"/>
        </testApplicationControllerDirectory>
      </testApplicationDirectory>
      <testLibraryDirectory/>
    </testsDirectory>
  </projectDirectory>
</projectProfile>
